{
  "data": [
    {
      "name": "Minnesota Timberwolves vs. Phoenix Suns",
      "type": "event",
      "id": "Z7r9jZ1A7_VZF1",
      "test": false,
      "height": 300,
      "span": 20,
      "url": "https://www.ticketmaster.com/event/Z7r9jZ1A7_VZF",
      "locale": "en-us",
      "images": [
        {
          "ratio": "3_2",
          "url": "https://s1.ticketm.net/dam/a/c70/98044e71-9085-471b-9f21-78525c745c70_TABLET_LANDSCAPE_3_2.jpg",
          "width": 1024,
          "height": 683,
          "fallback": false
        }
      ]
    },
    {
      "name": "22222",
      "type": "event",
      "id": "Z7r9jZ1A7_VZF2",
      "test": false,
      "height": 450,
      "span": 20,
      "url": "https://www.ticketmaster.com/event/Z7r9jZ1A7_VZF",
      "locale": "en-us",
      "images": [
        {
          "ratio": "3_2",
          "url": "https://s1.ticketm.net/dam/a/c70/98044e71-9085-471b-9f21-78525c745c70_TABLET_LANDSCAPE_3_2.jpg",
          "width": 1024,
          "height": 683,
          "fallback": false
        }
      ]
    },
    {
      "name": "333",
      "type": "event",
      "id": "Z7r9jZ1A7_VZF3",
      "test": false,
      "height": 500,
      "span": 20,
      "url": "https://www.ticketmaster.com/event/Z7r9jZ1A7_VZF",
      "locale": "en-us",
      "images": [
        {
          "ratio": "3_2",
          "url": "https://s1.ticketm.net/dam/a/c70/98044e71-9085-471b-9f21-78525c745c70_TABLET_LANDSCAPE_3_2.jpg",
          "width": 1024,
          "height": 683,
          "fallback": false
        }
      ]
    }
  ]
}